LICENSE
MANIFEST.in
README.md
pyproject.toml
setup.py
aimmd/__init__.py
aimmd/_version.py
aimmd.egg-info/PKG-INFO
aimmd.egg-info/SOURCES.txt
aimmd.egg-info/dependency_links.txt
aimmd.egg-info/requires.txt
aimmd.egg-info/top_level.txt
aimmd/analysis/__init__.py
aimmd/analysis/gradient_movie.py
aimmd/analysis/hipr.py
aimmd/base/__init__.py
aimmd/base/rcmodel.py
aimmd/base/rcmodel_train_decision.py
aimmd/base/storage.py
aimmd/base/trainset.py
aimmd/base/utils.py
aimmd/coords/__init__.py
aimmd/coords/_symmetry.c
aimmd/coords/_symmetry.pyx
aimmd/coords/internal.py
aimmd/coords/symmetry.py
aimmd/coords/utils.py
aimmd/distributed/__init__.py
aimmd/distributed/_config.py
aimmd/distributed/committors.py
aimmd/distributed/config.py
aimmd/distributed/pathmovers.py
aimmd/distributed/pathsampling.py
aimmd/distributed/spselectors.py
aimmd/distributed/utils.py
aimmd/keras/__init__.py
aimmd/keras/layers.py
aimmd/keras/rcmodel.py
aimmd/keras/utils.py
aimmd/ops/__init__.py
aimmd/ops/hooks.py
aimmd/ops/selector.py
aimmd/ops/traininghook.py
aimmd/ops/utils.py
aimmd/pytorch/__init__.py
aimmd/pytorch/networks.py
aimmd/pytorch/optim.py
aimmd/pytorch/rcmodel.py
aimmd/pytorch/trainset_gpu.py
aimmd/pytorch/utils.py
aimmd/symreg/__init__.py
aimmd/symreg/losses.py
aimmd/symreg/optimize.py
aimmd/symreg/utils.py
tests/test_base.py
tests/test_coords.py
tests/test_keras.py
tests/test_ops.py
tests/test_pytorch.py
tests/test_storage.py